{
  "navigation": {
    "navOrder": 1,
    "link": "/"
  },
  "sections": [
    {
      "type": "hero",
      "heroImage": "hero-cropped.jpg",
      "title": "Transforming technology within the Department of Defense",
      "cta": "ABOUT US",
      "ctaLink": "/about"
    },
    {
      "type": "textWithCallout",
      "mdMain": "**We're on a mission.**\n\nThe Defense Digital Service (DDS) was first established by the Secretary of Defense in November 2015 as a SWAT team of nerds to provide the best in modern technology to bolster national defense. We bring in talent from both the private sector and within government to advance critical DoD initiatives.",
      "mdCallout": "**Doing work that matters by focusing our time and energy on high-priority undertakings.**",
      "alignByText": true
    },
    {
      "type": "iconSection",
      "icons": [
        {
          "icon": "highfive.svg",
          "title": "Who We Are",
          "cta": "MEET THE TEAM",
          "ctaLink": "/team",
          "details": "We are a SWAT team of nerds that provides the best in modern technical knowledge to bolster national defense."
        },
        {
          "icon": "icon-lightbulb.png",
          "title": "What We Do",
          "cta": "VIEW OUR WORK",
          "ctaLink": "/portfolio",
          "details": "We focus on high-impact projects that advance the DoD's most important initiatives that are critical to the well-being of service members, civilians, and core operations of the Department. "
        },
        {
          "icon": "icon-news.png",
          "title": "Media",
          "cta": "VIEW OUR MEDIA",
          "ctaLink": "/media",
          "details": "Check out DDS in the news, our latest announcements, our blog, and connect with us on Twitter and LinkedIn."
        }
      ]
    },
    {
      "type": "callToAction",
      "mdMain": "**We're focused on hiring the best to serve the best.**\n\nInterested in proving hoodies, hackers, and nerds have an important role to play in furthering national defense missions?",
      "mdCallout": "**Doing work that matters by focusing our time and energy on high-priority undertakings.**",
      "cta": "APPLY TO DDS TODAY",
      "ctaLink": "/join-us"
    }
  ]
}